sgnevent/base/__init__.py
sgnevent/bin/__init__.py
sgnevent/bin/dir_to_hop.py
sgnevent/sinks/__init__.py
sgnevent/sinks/hop.py
sgnevent/sources/__init__.py
sgnevent/sources/directory.py
sgn_event-0.0.3.1.dist-info/METADATA
sgn_event-0.0.3.1.dist-info/WHEEL
sgn_event-0.0.3.1.dist-info/entry_points.txt
sgn_event-0.0.3.1.dist-info/top_level.txt
sgn_event-0.0.3.1.dist-info/RECORD
