Metadata-Version: 2.1
Name: sgn-event
Version: 0.0.3.1
Summary: Streaming Graph Navigator - Event. A framework to help navigate events through a graph. The events must flow.
Author-email: Chad Hanna <crh184@psu.edu>
Project-URL: Homepage, https://git.ligo.org/greg/sgn-event
Project-URL: Issues, https://git.ligo.org/greg/sgn-event/issues
Classifier: Programming Language :: Python :: 3
Classifier: License :: OSI Approved :: Mozilla Public License 2.0 (MPL 2.0)
Classifier: Operating System :: OS Independent
Requires-Python: >=3.9
Requires-Dist: sgn
Requires-Dist: hop-client
